setdoc/__init__.py
setdoc/core/__init__.py
setdoc/core/cfg.toml
setdoc/tests/__init__.py
setdoc/tests/test_core.py
setdoc-1.2.8.dist-info/licenses/LICENSE.txt
setdoc-1.2.8.dist-info/METADATA
setdoc-1.2.8.dist-info/WHEEL
setdoc-1.2.8.dist-info/top_level.txt
setdoc-1.2.8.dist-info/RECORD
