Metadata-Version: 2.4
Name: setdoc
Version: 1.2.8
Summary: This project helps to set the doc string.
Author-email: Johannes <johannes.programming@gmail.com>
License: The MIT License (MIT)
Project-URL: Download, https://pypi.org/project/setdoc/#files
Project-URL: Index, https://pypi.org/project/setdoc/
Project-URL: Source, https://github.com/johannes-programming/setdoc/
Project-URL: Website, https://setdoc.johannes-programming.online/
Classifier: Development Status :: 5 - Production/Stable
Classifier: License :: OSI Approved :: MIT License
Classifier: Natural Language :: English
Classifier: Operating System :: OS Independent
Classifier: Programming Language :: Python
Classifier: Programming Language :: Python :: 3
Classifier: Programming Language :: Python :: 3 :: Only
Classifier: Typing :: Typed
Requires-Python: >=3.11
License-File: LICENSE.txt
Dynamic: license-file
